pymocky/__init__.py
pymocky/__main__.py
pymocky/cli.py
pymocky-1.3.0.dist-info/licenses/LICENSE.md
pymocky-1.3.0.dist-info/METADATA
pymocky-1.3.0.dist-info/WHEEL
pymocky-1.3.0.dist-info/entry_points.txt
pymocky-1.3.0.dist-info/top_level.txt
pymocky-1.3.0.dist-info/RECORD
