Metadata-Version: 2.4
Name: pymocky
Version: 1.3.0
Summary: Send push notification from command line for single or multiple targets
Home-page: https://github.com/paulocoutinhox/pymocky
Author: Paulo Coutinho
Author-email: paulocoutinhox@gmail.com
License: MIT
Classifier: License :: OSI Approved :: MIT License
Classifier: Programming Language :: Python
Classifier: Programming Language :: Python :: 3
Classifier: Programming Language :: Python :: 3.10
Classifier: Programming Language :: Python :: 3.11
Classifier: Programming Language :: Python :: 3.12
Classifier: Programming Language :: Python :: 3.13
Classifier: Programming Language :: Python :: 3.14
Classifier: Programming Language :: Python :: Implementation :: CPython
Classifier: Programming Language :: Python :: Implementation :: PyPy
Requires-Python: >=3.10.0
License-File: LICENSE.md
Requires-Dist: cherrypy>=18.0
Requires-Dist: cherrypy_cors
Requires-Dist: pyyaml
Requires-Dist: watchdog
Requires-Dist: colorama
Requires-Dist: requests
Requires-Dist: regex
Dynamic: author
Dynamic: author-email
Dynamic: classifier
Dynamic: description
Dynamic: home-page
Dynamic: license
Dynamic: license-file
Dynamic: requires-dist
Dynamic: requires-python
Dynamic: summary
